<?xml version="1.0" encoding="utf-8"?>
<Deputados>
  <Deputado>
    <numLegislatura>54</numLegislatura>
    <email>dep.claudioputy@camara.gov.br</email>
    <nomeProfissao>Economista, Eletricitário, Professor Universitário</nomeProfissao>
    <dataNascimento>02/08/1970</dataNascimento>
    <dataFalecimento>
    </dataFalecimento>
    <ufRepresentacaoAtual>PA</ufRepresentacaoAtual>
    <situacaoNaLegislaturaAtual>Em Exercício</situacaoNaLegislaturaAtual>
    <ideCadastro>160557</ideCadastro>
    <idParlamentarDeprecated>10078</idParlamentarDeprecated>
    <nomeParlamentarAtual>CLÁUDIO PUTY</nomeParlamentarAtual>
    <nomeCivil>CLAUDIO ALBERTO CASTELO BRANCO PUTY</nomeCivil>
    <sexo>M</sexo>
    <partidoAtual>
      <idPartido>PT</idPartido>
      <sigla>PT</sigla>
      <nome>Partido dos Trabalhadores</nome>
    </partidoAtual>
    <gabinete>
      <numero>480</numero>
      <anexo>3</anexo>
      <telefone>3215-5480</telefone>
    </gabinete>
    <comissoes>
      <comissao>
        <idOrgaoLegislativoCD>2004</idOrgaoLegislativoCD>
        <siglaComissao>CDC</siglaComissao>
        <nomeComissao>Comissão de Defesa do Consumidor</nomeComissao>
        <condicaoMembro>Suplente</condicaoMembro>
        <dataEntrada>01/03/2011</dataEntrada>
        <dataSaida>31/01/2012</dataSaida>
      </comissao>
      <comissao>
        <idOrgaoLegislativoCD>2008</idOrgaoLegislativoCD>
        <siglaComissao>CDEIC</siglaComissao>
        <nomeComissao>Comissão de Desenvolvimento Econômico, Indústria e Comércio</nomeComissao>
        <condicaoMembro>Suplente</condicaoMembro>
        <dataEntrada>07/03/2012</dataEntrada>
        <dataSaida>02/02/2013</dataSaida>
      </comissao>
      <comissao>
        <idOrgaoLegislativoCD>6855</idOrgaoLegislativoCD>
        <siglaComissao>CMO</siglaComissao>
        <nomeComissao>Comissão Mista de Planos, Orçamentos Públicos e Fiscalização</nomeComissao>
        <condicaoMembro>Suplente</condicaoMembro>
        <dataEntrada>27/03/2012</dataEntrada>
        <dataSaida>25/03/2013</dataSaida>
      </comissao>
      <comissao>
        <idOrgaoLegislativoCD>2004</idOrgaoLegislativoCD>
        <siglaComissao>CDC</siglaComissao>
        <nomeComissao>Comissão de Defesa do Consumidor</nomeComissao>
        <condicaoMembro>Suplente</condicaoMembro>
        <dataEntrada>22/05/2012</dataEntrada>
        <dataSaida>10/07/2012</dataSaida>
      </comissao>
      <comissao>
        <idOrgaoLegislativoCD>2016</idOrgaoLegislativoCD>
        <siglaComissao>CVT</siglaComissao>
        <nomeComissao>Comissão de Viação e Transportes</nomeComissao>
        <condicaoMembro>Suplente</condicaoMembro>
        <dataEntrada>05/03/2013</dataEntrada>
        <dataSaida>03/02/2014</dataSaida>
      </comissao>
      <comissao>
        <idOrgaoLegislativoCD>537089</idOrgaoLegislativoCD>
        <siglaComissao>PL562713</siglaComissao>
        <nomeComissao>Comissão Especial destinada a proferir parecer ao Projeto de Lei nº 5627, de 2013, do Poder Executivo, que "altera o Decreto-Lei nº 9.760, de 5 de setembro de 1946, o Decreto-Lei nº 2.398, de 21 de dezembro de 1987, a Lei nº 9.636, de 15 de maio de 1998, dispõe sobre o parcelamento e a remissão de dívidas patrimoniais com a União, e dá outras providências"</nomeComissao>
        <condicaoMembro>Suplente</condicaoMembro>
        <dataEntrada>20/08/2013</dataEntrada>
        <dataSaida>
        </dataSaida>
      </comissao>
      <comissao>
        <idOrgaoLegislativoCD>537127</idOrgaoLegislativoCD>
        <siglaComissao>CPITRAB</siglaComissao>
        <nomeComissao>Comissão Parlamentar de Inquérito destinada a apurar a exploração do trabalho infantil no Brasil e dá outras providências</nomeComissao>
        <condicaoMembro>Suplente</condicaoMembro>
        <dataEntrada>25/09/2013</dataEntrada>
        <dataSaida>
        </dataSaida>
      </comissao>
      <comissao>
        <idOrgaoLegislativoCD>2012</idOrgaoLegislativoCD>
        <siglaComissao>CME</siglaComissao>
        <nomeComissao>Comissão de Minas e Energia</nomeComissao>
        <condicaoMembro>Suplente</condicaoMembro>
        <dataEntrada>25/02/2014</dataEntrada>
        <dataSaida>
        </dataSaida>
      </comissao>
      <comissao>
        <idOrgaoLegislativoCD>6974</idOrgaoLegislativoCD>
        <siglaComissao>SUBMICRO</siglaComissao>
        <nomeComissao>Subcomissão Permanente de Micro e Pequenas Empresas</nomeComissao>
        <condicaoMembro>Suplente</condicaoMembro>
        <dataEntrada>01/04/2014</dataEntrada>
        <dataSaida>
        </dataSaida>
      </comissao>
      <comissao>
        <idOrgaoLegislativoCD>6855</idOrgaoLegislativoCD>
        <siglaComissao>CMO</siglaComissao>
        <nomeComissao>Comissão Mista de Planos, Orçamentos Públicos e Fiscalização</nomeComissao>
        <condicaoMembro>Suplente</condicaoMembro>
        <dataEntrada>02/04/2014</dataEntrada>
        <dataSaida>
        </dataSaida>
      </comissao>
      <comissao>
        <idOrgaoLegislativoCD>2010</idOrgaoLegislativoCD>
        <siglaComissao>CFT</siglaComissao>
        <nomeComissao>Comissão de Finanças e Tributação</nomeComissao>
        <condicaoMembro>Titular</condicaoMembro>
        <dataEntrada>01/03/2011</dataEntrada>
        <dataSaida>31/01/2012</dataSaida>
      </comissao>
      <comissao>
        <idOrgaoLegislativoCD>6972</idOrgaoLegislativoCD>
        <siglaComissao>SUBRETRI</siglaComissao>
        <nomeComissao>Subcomissão Especial da Reforma Tributária</nomeComissao>
        <condicaoMembro>Titular</condicaoMembro>
        <dataEntrada>13/04/2011</dataEntrada>
        <dataSaida>01/04/2014</dataSaida>
      </comissao>
      <comissao>
        <idOrgaoLegislativoCD>6977</idOrgaoLegislativoCD>
        <siglaComissao>CEXPARA</siglaComissao>
        <nomeComissao>Comissão Externa para acompanhar as investigações sobre os fatos e as circunstâncias que envolvem os desvios de recursos públicos ocorridos na Assembleia Legislativa do Estado do Pará.</nomeComissao>
        <condicaoMembro>Titular</condicaoMembro>
        <dataEntrada>27/04/2011</dataEntrada>
        <dataSaida>
        </dataSaida>
      </comissao>
      <comissao>
        <idOrgaoLegislativoCD>2010</idOrgaoLegislativoCD>
        <siglaComissao>CFT</siglaComissao>
        <nomeComissao>Comissão de Finanças e Tributação</nomeComissao>
        <condicaoMembro>Titular</condicaoMembro>
        <dataEntrada>07/03/2012</dataEntrada>
        <dataSaida>02/02/2013</dataSaida>
      </comissao>
      <comissao>
        <idOrgaoLegislativoCD>9138</idOrgaoLegislativoCD>
        <siglaComissao>CPITRAES</siglaComissao>
        <nomeComissao>Comissão Parlamentar de Inquérito destinada a investigar a exploração do trabalho escravo ou análogo ao de escravo, em atividades rurais e urbanas, de todo o território nacional.</nomeComissao>
        <condicaoMembro>Titular</condicaoMembro>
        <dataEntrada>28/03/2012</dataEntrada>
        <dataSaida>16/03/2013</dataSaida>
      </comissao>
      <comissao>
        <idOrgaoLegislativoCD>2010</idOrgaoLegislativoCD>
        <siglaComissao>CFT</siglaComissao>
        <nomeComissao>Comissão de Finanças e Tributação</nomeComissao>
        <condicaoMembro>Titular</condicaoMembro>
        <dataEntrada>05/03/2013</dataEntrada>
        <dataSaida>03/02/2014</dataSaida>
      </comissao>
      <comissao>
        <idOrgaoLegislativoCD>8736</idOrgaoLegislativoCD>
        <siglaComissao>PL346004</siglaComissao>
        <nomeComissao>Comissão Especial destinada a proferir parecer ao Projeto de Lei nº 3460, de 2004, do Sr. Walter Feldman, que "institui diretrizes para a Política Nacional de Planejamento Regional Urbano, cria o Sistema Nacional de Planejamento e Informações Regionais Urbanas e dá outras providências" (Estatuto da Metrópole)</nomeComissao>
        <condicaoMembro>Titular</condicaoMembro>
        <dataEntrada>13/03/2013</dataEntrada>
        <dataSaida>
        </dataSaida>
      </comissao>
      <comissao>
        <idOrgaoLegislativoCD>8919</idOrgaoLegislativoCD>
        <siglaComissao>PEC50610</siglaComissao>
        <nomeComissao>Comissão Especial destinada a apreciar e  proferir parecer à Proposta de Emenda à Constituição nº 506-A, de 2010, do Senado Federal, que "acrescenta artigo ao Ato das Disposições Constitucionais Transitórias (ADCT), para dispor sobre a prorrogação dos beneficios para a Zona Franca de Manaus, e dá outras providências" (prorroga até 31 de dezembro de 2029)</nomeComissao>
        <condicaoMembro>Titular</condicaoMembro>
        <dataEntrada>14/03/2013</dataEntrada>
        <dataSaida>05/08/2014</dataSaida>
      </comissao>
      <comissao>
        <idOrgaoLegislativoCD>536999</idOrgaoLegislativoCD>
        <siglaComissao>PLP22112</siglaComissao>
        <nomeComissao>Comissão Especial destinada a proferir parecer ao Projeto de Lei Complementar nº 221, de 2012, do Sr. Vaz de Lima, que "altera os Anexos da Lei Complementar nº 123, de 14 de dezembro de 2006, para permitir o abatimento de parcela dedutível do valor devido mensalmente pelo pagamento do Simples Nacional, conforme a faixa de renda da pessoa jurídica" (altera também o art. 18 da Lei Complementar nº 123, de 2006), e apensado</nomeComissao>
        <condicaoMembro>Titular</condicaoMembro>
        <dataEntrada>11/06/2013</dataEntrada>
        <dataSaida>07/08/2014</dataSaida>
      </comissao>
      <comissao>
        <idOrgaoLegislativoCD>537146</idOrgaoLegislativoCD>
        <siglaComissao>CEXSAOFE</siglaComissao>
        <nomeComissao>Comissão Externa, sem ônus para esta Casa, destinada a verificar denúncias sobre o assassinato de trabalhador rural no município de São Félix do Xingu - PA, bem como, avaliar que providencias estão sendo tomadas sobre o caso.</nomeComissao>
        <condicaoMembro>Titular</condicaoMembro>
        <dataEntrada>22/08/2013</dataEntrada>
        <dataSaida>
        </dataSaida>
      </comissao>
      <comissao>
        <idOrgaoLegislativoCD>9145</idOrgaoLegislativoCD>
        <siglaComissao>PEC19712</siglaComissao>
        <nomeComissao>Comissão Especial destinada a proferir parecer à Proposta de Emenda à Constituição nº 197-A, de 2012, do Senado Federal, que "altera o § 2º do art. 155 da Constituição Federal, para modificar a sistemática de cobrança do imposto sobre operações relativas à circulação de mercadorias e sobre prestações de serviços de transporte interestadual e intermunicipal e de comunicação incidente sobre as operações e prestações realizadas de forma não presencial e que destinem bens e serviços a consumidor final localizado em outro Estado"</nomeComissao>
        <condicaoMembro>Titular</condicaoMembro>
        <dataEntrada>04/12/2013</dataEntrada>
        <dataSaida>
        </dataSaida>
      </comissao>
      <comissao>
        <idOrgaoLegislativoCD>537201</idOrgaoLegislativoCD>
        <siglaComissao>GTREFTR</siglaComissao>
        <nomeComissao>Grupo de Trabalho para análise, estudo e formulação de proposições relacionadas à Reforma da Legislação Tributária Nacional</nomeComissao>
        <condicaoMembro>Titular</condicaoMembro>
        <dataEntrada>04/02/2014</dataEntrada>
        <dataSaida>
        </dataSaida>
      </comissao>
      <comissao>
        <idOrgaoLegislativoCD>2010</idOrgaoLegislativoCD>
        <siglaComissao>CFT</siglaComissao>
        <nomeComissao>Comissão de Finanças e Tributação</nomeComissao>
        <condicaoMembro>Titular</condicaoMembro>
        <dataEntrada>25/02/2014</dataEntrada>
        <dataSaida>
        </dataSaida>
      </comissao>
      <comissao>
        <idOrgaoLegislativoCD>537216</idOrgaoLegislativoCD>
        <siglaComissao>PEC09211</siglaComissao>
        <nomeComissao>Comissão Especial destinada a proferir parecer à Proposta de Emenda à Constituição nº 92-A, de 2011, do Sr. Cláudio Puty e outros, que "acrescenta parágrafo ao art. 155 da Constituição" (estabelece a incidência de ICMS para exportação de bens minerais primários ou semi-elaborados) e apensada</nomeComissao>
        <condicaoMembro>Titular</condicaoMembro>
        <dataEntrada>28/05/2014</dataEntrada>
        <dataSaida>
        </dataSaida>
      </comissao>
    </comissoes>
    <cargosComissoes>
      <cargoComissoes>
        <idOrgaoLegislativoCD>536999</idOrgaoLegislativoCD>
        <siglaComissao>PLP22112</siglaComissao>
        <nomeComissao>Comissão Especial destinada a proferir parecer ao Projeto de Lei Complementar nº 221, de 2012, do Sr. Vaz de Lima, que "altera os Anexos da Lei Complementar nº 123, de 14 de dezembro de 2006, para permitir o abatimento de parcela dedutível do valor devido mensalmente pelo pagamento do Simples Nacional, conforme a faixa de renda da pessoa jurídica" (altera também o art. 18 da Lei Complementar nº 123, de 2006), e apensado</nomeComissao>
        <idCargo>50</idCargo>
        <nomeCargo>Relator</nomeCargo>
        <dataEntrada>12/06/2013</dataEntrada>
        <dataSaida>
        </dataSaida>
      </cargoComissoes>
      <cargoComissoes>
        <idOrgaoLegislativoCD>537146</idOrgaoLegislativoCD>
        <siglaComissao>CEXSAOFE</siglaComissao>
        <nomeComissao>Comissão Externa, sem ônus para esta Casa, destinada a verificar denúncias sobre o assassinato de trabalhador rural no município de São Félix do Xingu - PA, bem como, avaliar que providencias estão sendo tomadas sobre o caso.</nomeComissao>
        <idCargo>14</idCargo>
        <nomeCargo>Coordenador</nomeCargo>
        <dataEntrada>22/08/2013</dataEntrada>
        <dataSaida>
        </dataSaida>
      </cargoComissoes>
      <cargoComissoes>
        <idOrgaoLegislativoCD>6977</idOrgaoLegislativoCD>
        <siglaComissao>CEXPARA</siglaComissao>
        <nomeComissao>Comissão Externa para acompanhar as investigações sobre os fatos e as circunstâncias que envolvem os desvios de recursos públicos ocorridos na Assembleia Legislativa do Estado do Pará.</nomeComissao>
        <idCargo>14</idCargo>
        <nomeCargo>Coordenador</nomeCargo>
        <dataEntrada>27/04/2011</dataEntrada>
        <dataSaida>
        </dataSaida>
      </cargoComissoes>
      <cargoComissoes>
        <idOrgaoLegislativoCD>9138</idOrgaoLegislativoCD>
        <siglaComissao>CPITRAES</siglaComissao>
        <nomeComissao>Comissão Parlamentar de Inquérito destinada a investigar a exploração do trabalho escravo ou análogo ao de escravo, em atividades rurais e urbanas, de todo o território nacional.</nomeComissao>
        <idCargo>1</idCargo>
        <nomeCargo>Presidente</nomeCargo>
        <dataEntrada>28/03/2012</dataEntrada>
        <dataSaida>16/03/2013</dataSaida>
      </cargoComissoes>
      <cargoComissoes>
        <idOrgaoLegislativoCD>2010</idOrgaoLegislativoCD>
        <siglaComissao>CFT</siglaComissao>
        <nomeComissao>Comissão de Finanças e Tributação</nomeComissao>
        <idCargo>1</idCargo>
        <nomeCargo>Presidente</nomeCargo>
        <dataEntrada>02/03/2011</dataEntrada>
        <dataSaida>07/03/2012</dataSaida>
      </cargoComissoes>
    </cargosComissoes>
    <periodosExercicio>
      <periodoExercicio>
        <siglaUFRepresentacao>PA</siglaUFRepresentacao>
        <situacaoExercicio>Titular</situacaoExercicio>
        <dataInicio>01/02/2011</dataInicio>
        <dataFim>
        </dataFim>
        <idCausaFimExercicio>
        </idCausaFimExercicio>
        <descricaoCausaFimExercicio>
        </descricaoCausaFimExercicio>
        <idCadastroParlamentarAnterior>
        </idCadastroParlamentarAnterior>
      </periodoExercicio>
    </periodosExercicio>
    <historicoNomeParlamentar />
    <filiacoesPartidarias />
    <historicoLider />
  </Deputado>
</Deputados>