<?xml version="1.0" encoding="utf-8"?>
<Deputados>
  <Deputado>
    <numLegislatura>54</numLegislatura>
    <email>dep.alexandretoledo@camara.gov.br</email>
    <nomeProfissao>
    </nomeProfissao>
    <dataNascimento>28/03/1956</dataNascimento>
    <dataFalecimento>
    </dataFalecimento>
    <ufRepresentacaoAtual>AL</ufRepresentacaoAtual>
    <situacaoNaLegislaturaAtual>Em Exercício</situacaoNaLegislaturaAtual>
    <ideCadastro>169712</ideCadastro>
    <idParlamentarDeprecated>10241</idParlamentarDeprecated>
    <nomeParlamentarAtual>ALEXANDRE TOLEDO</nomeParlamentarAtual>
    <nomeCivil>ALEXANDRE DE MELO TOLEDO</nomeCivil>
    <sexo>M</sexo>
    <partidoAtual>
      <idPartido>PSB</idPartido>
      <sigla>PSB</sigla>
      <nome>Partido Socialista Brasileiro</nome>
    </partidoAtual>
    <gabinete>
      <numero>379</numero>
      <anexo>3</anexo>
      <telefone>3215-5379</telefone>
    </gabinete>
    <comissoes>
      <comissao>
        <idOrgaoLegislativoCD>6174</idOrgaoLegislativoCD>
        <siglaComissao>CMADS</siglaComissao>
        <nomeComissao>Comissão de Meio Ambiente e Desenvolvimento Sustentável</nomeComissao>
        <condicaoMembro>Suplente</condicaoMembro>
        <dataEntrada>05/03/2013</dataEntrada>
        <dataSaida>17/10/2013</dataSaida>
      </comissao>
      <comissao>
        <idOrgaoLegislativoCD>2012</idOrgaoLegislativoCD>
        <siglaComissao>CME</siglaComissao>
        <nomeComissao>Comissão de Minas e Energia</nomeComissao>
        <condicaoMembro>Suplente</condicaoMembro>
        <dataEntrada>16/10/2013</dataEntrada>
        <dataSaida>03/02/2014</dataSaida>
      </comissao>
      <comissao>
        <idOrgaoLegislativoCD>537020</idOrgaoLegislativoCD>
        <siglaComissao>CEDES</siglaComissao>
        <nomeComissao>Centro de Estudos e Debates Estratégicos</nomeComissao>
        <condicaoMembro>Suplente</condicaoMembro>
        <dataEntrada>17/10/2013</dataEntrada>
        <dataSaida>
        </dataSaida>
      </comissao>
      <comissao>
        <idOrgaoLegislativoCD>537213</idOrgaoLegislativoCD>
        <siglaComissao>PEC49110</siglaComissao>
        <nomeComissao>Comissão Especial destinada a proferir parecer à Proposta de Emenda à Constituição nº 491, de 2010, do Sr. Luiz Carlos Hauly e outros, que "acresce incisos ao art. 150, VI e art. 155, X da Constituição Federal" (proíbe a criação de imposto incidente sobre insumos agrícolas, pecuária, alimentos para o consumo humano e medicamentos), e apensadas</nomeComissao>
        <condicaoMembro>Suplente</condicaoMembro>
        <dataEntrada>12/05/2014</dataEntrada>
        <dataSaida>
        </dataSaida>
      </comissao>
      <comissao>
        <idOrgaoLegislativoCD>2012</idOrgaoLegislativoCD>
        <siglaComissao>CME</siglaComissao>
        <nomeComissao>Comissão de Minas e Energia</nomeComissao>
        <condicaoMembro>Suplente</condicaoMembro>
        <dataEntrada>25/02/2014</dataEntrada>
        <dataSaida>
        </dataSaida>
      </comissao>
      <comissao>
        <idOrgaoLegislativoCD>6066</idOrgaoLegislativoCD>
        <siglaComissao>CTUR</siglaComissao>
        <nomeComissao>Comissão de Turismo</nomeComissao>
        <condicaoMembro>Suplente</condicaoMembro>
        <dataEntrada>25/02/2014</dataEntrada>
        <dataSaida>
        </dataSaida>
      </comissao>
      <comissao>
        <idOrgaoLegislativoCD>2001</idOrgaoLegislativoCD>
        <siglaComissao>CAPADR</siglaComissao>
        <nomeComissao>Comissão de Agricultura, Pecuária, Abastecimento e Desenvolvimento Rural</nomeComissao>
        <condicaoMembro>Titular</condicaoMembro>
        <dataEntrada>05/03/2013</dataEntrada>
        <dataSaida>03/02/2014</dataSaida>
      </comissao>
      <comissao>
        <idOrgaoLegislativoCD>537130</idOrgaoLegislativoCD>
        <siglaComissao>SUBCARTL</siglaComissao>
        <nomeComissao>Subcomissão Permanente de Combate à Cartelização do Agronegócio no Brasil, destinada a discutir e oferecer soluções às práticas monopolistas em prejuízo dos produtores rurais brasileiros.</nomeComissao>
        <condicaoMembro>Titular</condicaoMembro>
        <dataEntrada>14/08/2013</dataEntrada>
        <dataSaida>
        </dataSaida>
      </comissao>
      <comissao>
        <idOrgaoLegislativoCD>8849</idOrgaoLegislativoCD>
        <siglaComissao>PL533209</siglaComissao>
        <nomeComissao>Comissão Especial destinada a apreciar e proferir parecer ao Projeto de Lei nº 5332, de 2009, da Sra. Elcione Barbalho, que "cria o 'pão brasileiro', a ser produzido com farinha de trigo adicionada de farinha de mandioca refinada, de farinha de raspa de mandioca ou de fécula de mandioca, adquiridos pelo poder público, e estabelece regime tributário especial para a farinha de trigo misturada, e dá outras providências"</nomeComissao>
        <condicaoMembro>Titular</condicaoMembro>
        <dataEntrada>08/10/2013</dataEntrada>
        <dataSaida>
        </dataSaida>
      </comissao>
      <comissao>
        <idOrgaoLegislativoCD>9145</idOrgaoLegislativoCD>
        <siglaComissao>PEC19712</siglaComissao>
        <nomeComissao>Comissão Especial destinada a proferir parecer à Proposta de Emenda à Constituição nº 197-A, de 2012, do Senado Federal, que "altera o § 2º do art. 155 da Constituição Federal, para modificar a sistemática de cobrança do imposto sobre operações relativas à circulação de mercadorias e sobre prestações de serviços de transporte interestadual e intermunicipal e de comunicação incidente sobre as operações e prestações realizadas de forma não presencial e que destinem bens e serviços a consumidor final localizado em outro Estado"</nomeComissao>
        <condicaoMembro>Titular</condicaoMembro>
        <dataEntrada>13/02/2014</dataEntrada>
        <dataSaida>
        </dataSaida>
      </comissao>
      <comissao>
        <idOrgaoLegislativoCD>2001</idOrgaoLegislativoCD>
        <siglaComissao>CAPADR</siglaComissao>
        <nomeComissao>Comissão de Agricultura, Pecuária, Abastecimento e Desenvolvimento Rural</nomeComissao>
        <condicaoMembro>Titular</condicaoMembro>
        <dataEntrada>25/02/2014</dataEntrada>
        <dataSaida>
        </dataSaida>
      </comissao>
      <comissao>
        <idOrgaoLegislativoCD>6855</idOrgaoLegislativoCD>
        <siglaComissao>CMO</siglaComissao>
        <nomeComissao>Comissão Mista de Planos, Orçamentos Públicos e Fiscalização</nomeComissao>
        <condicaoMembro>Titular</condicaoMembro>
        <dataEntrada>25/03/2014</dataEntrada>
        <dataSaida>
        </dataSaida>
      </comissao>
    </comissoes>
    <cargosComissoes />
    <periodosExercicio>
      <periodoExercicio>
        <siglaUFRepresentacao>AL</siglaUFRepresentacao>
        <situacaoExercicio>Efetivado</situacaoExercicio>
        <dataInicio>14/06/2012</dataInicio>
        <dataFim>18/06/2012</dataFim>
        <idCausaFimExercicio>12</idCausaFimExercicio>
        <descricaoCausaFimExercicio>Secretário de Estado</descricaoCausaFimExercicio>
        <idCadastroParlamentarAnterior>76420</idCadastroParlamentarAnterior>
      </periodoExercicio>
      <periodoExercicio>
        <siglaUFRepresentacao>AL</siglaUFRepresentacao>
        <situacaoExercicio>Efetivado</situacaoExercicio>
        <dataInicio>28/01/2013</dataInicio>
        <dataFim>10/07/2014</dataFim>
        <idCausaFimExercicio>20</idCausaFimExercicio>
        <descricaoCausaFimExercicio>Licença Conjunta Consecutiva</descricaoCausaFimExercicio>
        <idCadastroParlamentarAnterior>76420</idCadastroParlamentarAnterior>
      </periodoExercicio>
      <periodoExercicio>
        <siglaUFRepresentacao>AL</siglaUFRepresentacao>
        <situacaoExercicio>Efetivado</situacaoExercicio>
        <dataInicio>09/11/2014</dataInicio>
        <dataFim>
        </dataFim>
        <idCausaFimExercicio>
        </idCausaFimExercicio>
        <descricaoCausaFimExercicio>
        </descricaoCausaFimExercicio>
        <idCadastroParlamentarAnterior>
        </idCadastroParlamentarAnterior>
      </periodoExercicio>
    </periodosExercicio>
    <historicoNomeParlamentar />
    <filiacoesPartidarias>
      <filiacaoPartidaria>
        <idPartidoAnterior>PSDB</idPartidoAnterior>
        <siglaPartidoAnterior>PSDB</siglaPartidoAnterior>
        <nomePartidoAnterior>Partido da Social Democracia Brasileira</nomePartidoAnterior>
        <idPartidoPosterior>S.PART.</idPartidoPosterior>
        <siglaPartidoPosterior>S.PART.</siglaPartidoPosterior>
        <nomePartidoPosterior>Sem Partido</nomePartidoPosterior>
        <dataFiliacaoPartidoPosterior>25/09/2013</dataFiliacaoPartidoPosterior>
      </filiacaoPartidaria>
      <filiacaoPartidaria>
        <idPartidoAnterior>S.PART.</idPartidoAnterior>
        <siglaPartidoAnterior>S.PART.</siglaPartidoAnterior>
        <nomePartidoAnterior>Sem Partido</nomePartidoAnterior>
        <idPartidoPosterior>PSB</idPartidoPosterior>
        <siglaPartidoPosterior>PSB</siglaPartidoPosterior>
        <nomePartidoPosterior>Partido Socialista Brasileiro</nomePartidoPosterior>
        <dataFiliacaoPartidoPosterior>02/10/2013</dataFiliacaoPartidoPosterior>
      </filiacaoPartidaria>
    </filiacoesPartidarias>
    <historicoLider>
      <itemHistoricoLider>
        <idHistoricoLider>169712</idHistoricoLider>
        <idCargoLideranca>V</idCargoLideranca>
        <descricaoCargoLideranca>Vice-Líder</descricaoCargoLideranca>
        <numOrdemCargo>9</numOrdemCargo>
        <dataDesignacao>22/02/2013</dataDesignacao>
        <dataTermino>25/09/2013</dataTermino>
        <codigoUnidadeLideranca>P</codigoUnidadeLideranca>
        <siglaUnidadeLideranca>PSDB</siglaUnidadeLideranca>
        <idBlocoPartido>PSDB</idBlocoPartido>
      </itemHistoricoLider>
    </historicoLider>
  </Deputado>
</Deputados>